{
  "CommitteeNumber": "332",
  "CommitteeDate": "07/08/2002",
  "KnessetNumber": "15",
  "participantsDetails": {
    "יוסי כץ": {
      "HebrewName": "יוסי כץ",
      "EnglishName": "Katz Yossi",
      "Gender": "Male",
      "SpokenWords": 1179
    },
    "אפי אושעיה": {
      "HebrewName": "אפי אושעיה",
      "EnglishName": "Oshaya Efi",
      "Gender": "Male",
      "SpokenWords": 84
    },
    "מיכאל איתן": {
      "HebrewName": "מיכאל איתן",
      "EnglishName": "Eitan Michael",
      "Gender": "Male",
      "SpokenWords": 529
    },
    "זאב בוים": {
      "HebrewName": "זאב בוים",
      "EnglishName": "Boim Ze`ev",
      "Gender": "Male",
      "SpokenWords": 743
    },
    "משה גפני": {
      "HebrewName": "משה גפני",
      "EnglishName": "Gafni Moshe",
      "Gender": "Male",
      "SpokenWords": 0
    },
    "נסים זאב": {
      "HebrewName": "נסים זאב",
      "EnglishName": "Zeev Nissim",
      "Gender": "Male",
      "SpokenWords": 346
    },
    "שאול יהלום": {
      "HebrewName": "שאול יהלום",
      "EnglishName": "Yahalom Shaul",
      "Gender": "Male",
      "SpokenWords": 321
    },
    "אלי כהן": {
      "HebrewName": "אלי כהן",
      "EnglishName": "Cohen Eli",
      "Gender": "Male",
      "SpokenWords": 156
    },
    "סופה לנדבר": {
      "HebrewName": "סופה לנדבר",
      "EnglishName": "Landver Sofa",
      "Gender": "Female",
      "SpokenWords": 0
    },
    "מרדכי משעני": {
      "HebrewName": "מרדכי משעני",
      "EnglishName": "Mishani Mordechai",
      "Gender": "Male",
      "SpokenWords": 0
    },
    "יאיר פרץ": {
      "HebrewName": "יאיר פרץ",
      "EnglishName": "Peretz Yair",
      "Gender": "Male",
      "SpokenWords": 37
    },
    "נחמה רונן": {
      "HebrewName": "נחמה רונן",
      "EnglishName": "Ronen Nehama",
      "Gender": "Female",
      "SpokenWords": 0
    },
    "יורי שטרן": {
      "HebrewName": "יורי שטרן",
      "EnglishName": "Shtern Yuri",
      "Gender": "Male",
      "SpokenWords": 55
    },
    "ויצמן שירי": {
      "HebrewName": "ויצמן שירי",
      "EnglishName": "Shiry Wizman",
      "Gender": "Male",
      "SpokenWords": 583
    }
  }
}