{
  "CommitteeNumber": "154",
  "CommitteeDate": "10/24/2007",
  "KnessetNumber": "17",
  "participantsDetails": {
    "דוד טל": {
      "HebrewName": "דוד טל",
      "EnglishName": "Tal David",
      "Gender": "Male",
      "SpokenWords": 570
    },
    "קולט אביטל": {
      "HebrewName": "קולט אביטל",
      "EnglishName": "Avital Colette",
      "Gender": "Female",
      "SpokenWords": 4
    },
    "יולי יואל אדלשטיין": {
      "HebrewName": "יולי יואל אדלשטיין",
      "EnglishName": "Edelstein Yuli-Yoel",
      "Gender": "Male",
      "SpokenWords": 50
    },
    "דוד אזולאי": {
      "HebrewName": "דוד אזולאי",
      "EnglishName": "Azoulay David",
      "Gender": "Male",
      "SpokenWords": 0
    },
    "אריה אלדד": {
      "HebrewName": "אריה אלדד",
      "EnglishName": "Eldad Arieh",
      "Gender": "Male",
      "SpokenWords": 159
    },
    "אלי אפללו": {
      "HebrewName": "אלי אפללו",
      "EnglishName": "Aflalo Eli",
      "Gender": "Male",
      "SpokenWords": 0
    },
    "אורי אריאל": {
      "HebrewName": "אורי אריאל",
      "EnglishName": "Ariel Uri Yehuda",
      "Gender": "Male",
      "SpokenWords": 0
    },
    "אליהו גבאי": {
      "HebrewName": "אליהו גבאי",
      "EnglishName": "Gabbay Eliahu",
      "Gender": "Male",
      "SpokenWords": 0
    },
    "יצחק גלנטי": {
      "HebrewName": "יצחק גלנטי",
      "EnglishName": "Galantee Itshac",
      "Gender": "Male",
      "SpokenWords": 16
    },
    "נסים זאב": {
      "HebrewName": "נסים זאב",
      "EnglishName": "Zeev Nissim",
      "Gender": "Male",
      "SpokenWords": 124
    },
    "יצחק זיו": {
      "HebrewName": "יצחק זיו",
      "EnglishName": "Ziv Izhak",
      "Gender": "Male",
      "SpokenWords": 0
    },
    "אחמד טיבי": {
      "HebrewName": "אחמד טיבי",
      "EnglishName": "Tibi Ahmad",
      "Gender": "Male",
      "SpokenWords": 308
    },
    "שלי יחימוביץ": {
      "HebrewName": "שלי יחימוביץ",
      "EnglishName": "Yachimovich Shelly",
      "Gender": "Female",
      "SpokenWords": 231
    },
    "יעקב מרגי": {
      "HebrewName": "יעקב מרגי",
      "EnglishName": "Margi Yakov",
      "Gender": "Male",
      "SpokenWords": 117
    },
    "גדעון סער": {
      "HebrewName": "גדעון סער",
      "EnglishName": "Sa`ar Gideon",
      "Gender": "Male",
      "SpokenWords": 530
    },
    "מאיר פרוש": {
      "HebrewName": "מאיר פרוש",
      "EnglishName": "Porush Meir",
      "Gender": "Male",
      "SpokenWords": 71
    },
    "רונית תירוש": {
      "HebrewName": "רונית תירוש",
      "EnglishName": "Tirosh Ronit",
      "Gender": "Female",
      "SpokenWords": 0
    }
  }
}