{
  "CommitteeNumber": "21",
  "CommitteeDate": "01/29/2008",
  "KnessetNumber": "17",
  "participantsDetails": {
    "דוד טל": {
      "HebrewName": "דוד טל",
      "EnglishName": "Tal David",
      "Gender": "Male",
      "SpokenWords": 1727
    },
    "קולט אביטל": {
      "HebrewName": "קולט אביטל",
      "EnglishName": "Avital Colette",
      "Gender": "Female",
      "SpokenWords": 518
    },
    "יולי יואל אדלשטיין": {
      "HebrewName": "יולי יואל אדלשטיין",
      "EnglishName": "Edelstein Yuli-Yoel",
      "Gender": "Male",
      "SpokenWords": 0
    },
    "אורי יהודה אריאל": {
      "HebrewName": "אורי יהודה אריאל",
      "EnglishName": "Ariel Uri Yehuda",
      "Gender": "Male",
      "SpokenWords": 0
    },
    "מוחמד ברכה": {
      "HebrewName": "מוחמד ברכה",
      "EnglishName": "Barakeh Mohammad",
      "Gender": "Male",
      "SpokenWords": 31
    },
    "אלחנן גלזר": {
      "HebrewName": "אלחנן גלזר",
      "EnglishName": "Glazer Elhanan",
      "Gender": "Male",
      "SpokenWords": 0
    },
    "נאדיה חילו": {
      "HebrewName": "נאדיה חילו",
      "EnglishName": "Hilou Nadia",
      "Gender": "Female",
      "SpokenWords": 441
    },
    "יואל חסון": {
      "HebrewName": "יואל חסון",
      "EnglishName": "Hasson Yoel",
      "Gender": "Male",
      "SpokenWords": 323
    },
    "אסתרינה טרטמן": {
      "HebrewName": "אסתרינה טרטמן",
      "EnglishName": "Tartman Esterina",
      "Gender": "Female",
      "SpokenWords": 1686
    },
    "יעקב מרגי": {
      "HebrewName": "יעקב מרגי",
      "EnglishName": "Margi Yakov",
      "Gender": "Male",
      "SpokenWords": 33
    },
    "מאיר פרוש": {
      "HebrewName": "מאיר פרוש",
      "EnglishName": "Porush Meir",
      "Gender": "Male",
      "SpokenWords": 0
    }
  }
}