{
  "CommitteeNumber": "138",
  "CommitteeDate": "7/16/2007",
  "KnessetNumber": "17",
  "participantsDetails": {
    "יולי יואל אדלשטיין": {
      "HebrewName": "יולי יואל אדלשטיין",
      "EnglishName": "Edelstein Yuli-Yoel",
      "Gender": "Male",
      "SpokenWords": 24
    },
    "דוד אזולאי": {
      "HebrewName": "דוד אזולאי",
      "EnglishName": "Azoulay David",
      "Gender": "Male",
      "SpokenWords": 5
    },
    "אורי אריאל": {
      "HebrewName": "אורי אריאל",
      "EnglishName": "Ariel Uri Yehuda",
      "Gender": "Male",
      "SpokenWords": 35
    },
    "אליהו גבאי": {
      "HebrewName": "אליהו גבאי",
      "EnglishName": "Gabbay Eliahu",
      "Gender": "Male",
      "SpokenWords": 0
    },
    "זהבה גלאון": {
      "HebrewName": "זהבה גלאון",
      "EnglishName": "Galon Zehava",
      "Gender": "Female",
      "SpokenWords": 440
    },
    "נסים זאב": {
      "HebrewName": "נסים זאב",
      "EnglishName": "Zeev Nissim",
      "Gender": "Male",
      "SpokenWords": 359
    },
    "נדיה חילו": {
      "HebrewName": "נדיה חילו",
      "EnglishName": "Hilou Nadia",
      "Gender": "Female",
      "SpokenWords": 0
    },
    "אסתרינה טרטמן": {
      "HebrewName": "אסתרינה טרטמן",
      "EnglishName": "Tartman Esterina",
      "Gender": "Female",
      "SpokenWords": 164
    },
    "שלי יחימוביץ'": {
      "HebrewName": "שלי יחימוביץ'",
      "EnglishName": "Yachimovich Shelly",
      "Gender": "Female",
      "SpokenWords": 0
    },
    "יורם מרציאנו": {
      "HebrewName": "יורם מרציאנו",
      "EnglishName": "Marciano Yoram",
      "Gender": "Male",
      "SpokenWords": 102
    },
    "גדעון סער": {
      "HebrewName": "גדעון סער",
      "EnglishName": "Sa`ar Gideon",
      "Gender": "Male",
      "SpokenWords": 1139
    },
    "מאיר פרוש": {
      "HebrewName": "מאיר פרוש",
      "EnglishName": "Porush Meir",
      "Gender": "Male",
      "SpokenWords": 46
    },
    "ראובן ריבלין": {
      "HebrewName": "ראובן ריבלין",
      "EnglishName": "Rivlin Reuven",
      "Gender": "Male",
      "SpokenWords": 27
    },
    "משה שרוני": {
      "HebrewName": "משה שרוני",
      "EnglishName": "Sharoni Moshe",
      "Gender": "Male",
      "SpokenWords": 27
    }
  }
}