{
  "CommitteeNumber": "1",
  "CommitteeDate": "07/14/2010",
  "KnessetNumber": "18",
  "participantsDetails": {
    "יריב לוין": {
      "HebrewName": "יריב לוין",
      "EnglishName": "Levin Yariv",
      "Gender": "Male",
      "SpokenWords": 1984
    },
    "רחל אדטו": {
      "HebrewName": "רחל אדטו",
      "EnglishName": "Adatto Rachel",
      "Gender": "Female",
      "SpokenWords": 21
    },
    "אורי אורבך": {
      "HebrewName": "אורי אורבך",
      "EnglishName": "Orbach Uri",
      "Gender": "Male",
      "SpokenWords": 0
    },
    "חיים אורון": {
      "HebrewName": "חיים אורון",
      "EnglishName": "Oron Chaim",
      "Gender": "Male",
      "SpokenWords": 122
    },
    "אריה אלדד": {
      "HebrewName": "אריה אלדד",
      "EnglishName": "Eldad Arieh",
      "Gender": "Male",
      "SpokenWords": 0
    },
    "זאב אלקין": {
      "HebrewName": "זאב אלקין",
      "EnglishName": "Elkin Zeev",
      "Gender": "Male",
      "SpokenWords": 0
    },
    "חיים אמסלם": {
      "HebrewName": "חיים אמסלם",
      "EnglishName": "Amsellem Chaim",
      "Gender": "Male",
      "SpokenWords": 0
    },
    "דני דנון": {
      "HebrewName": "דני דנון",
      "EnglishName": "Danon Danny",
      "Gender": "Male",
      "SpokenWords": 10
    },
    "ציפי חוטובלי": {
      "HebrewName": "ציפי חוטובלי",
      "EnglishName": "Hotovely Tzipi",
      "Gender": "Female",
      "SpokenWords": 0
    },
    "איתן כבל": {
      "HebrewName": "איתן כבל",
      "EnglishName": "Cabel Eitan",
      "Gender": "Male",
      "SpokenWords": 0
    },
    "שלמה מולה": {
      "HebrewName": "שלמה מולה",
      "EnglishName": "Molla Shlomo (Neguse)",
      "Gender": "Male",
      "SpokenWords": 28
    },
    "אברהם מיכאלי": {
      "HebrewName": "אברהם מיכאלי",
      "EnglishName": "Michaeli Avraham",
      "Gender": "Male",
      "SpokenWords": 0
    },
    "כרמל שאמה": {
      "HebrewName": "כרמל שאמה",
      "EnglishName": "Shama Hacohen Carmel",
      "Gender": "Male",
      "SpokenWords": 0
    },
    "עתניאל שנלר": {
      "HebrewName": "עתניאל שנלר",
      "EnglishName": "Schneller Otniel",
      "Gender": "Male",
      "SpokenWords": 0
    }
  }
}