{
  "CommitteeNumber": "321",
  "CommitteeDate": "01/22/2018",
  "KnessetNumber": "20",
  "participantsDetails": {
    "מכלוף מיקי זוהר": {
      "HebrewName": "מכלוף מיקי זוהר",
      "EnglishName": "Zohar Miki",
      "Gender": "Male",
      "SpokenWords": 632
    },
    "רוברט אילטוב": {
      "HebrewName": "רוברט אילטוב",
      "EnglishName": "Ilatov Robert",
      "Gender": "Male",
      "SpokenWords": 23
    },
    "דוד ביטן": {
      "HebrewName": "דוד ביטן",
      "EnglishName": "Bitan David",
      "Gender": "Male",
      "SpokenWords": 0
    },
    "אחמד טיבי": {
      "HebrewName": "אחמד טיבי",
      "EnglishName": "Tibi Ahmad",
      "Gender": "Male",
      "SpokenWords": 408
    },
    "אברהם נגוסה": {
      "HebrewName": "אברהם נגוסה",
      "EnglishName": "Neguise Avraham",
      "Gender": "Male",
      "SpokenWords": 147
    },
    "רועי פולקמן": {
      "HebrewName": "רועי פולקמן",
      "EnglishName": "Folkman Roy",
      "Gender": "Male",
      "SpokenWords": 16
    }
  }
}